{
    "FIELD_MAP_GSHEET": {
      "UID": "id",
      "זמינות": "quantity",
      "עלות": "cost",
      "דילר 1": "price_1",
      "דילר 2": "price_2",
      "דילר 3": "price_3",
      "ס.לפני": "price",
      "תאור מקוצר": "title",
      "תיאור": "desc", 
      "מק\"ט": "sku"
    },
    "FIELD_MAP_WEBSITE": {
      "id": "id",
      "sku": "sku",
      "stock_quantity": "quantity",
      "manage_stock": "visible",
      "price": "price",
      "sale_price": "sale_price",
      "name": "title",
      "short_description": "desc",
      "cost": "cost",
      "b2bking_regular_product_price_group_2424": "price_1",
      "b2bking_regular_product_price_group_2425": "price_2",
      "b2bking_regular_product_price_group_2426": "price_3",
      "acf-field_65fc592a937b9": "cost_"
    },
    "FILED_DATA_TYPES": {
      "id": "Int32", 
      "quantity": "Int8",
      "cost": "float64", 
      "price_1": "float64",
      "price_2": "float64",
      "price_3": "float64",
      "price": "float64",
      "title": "object",
      "desc": "object",
      "visible": "bool"
    }, 
    "FILED_DATA_TYPES_WEB": {
      "id": "Int32", 
      "quantity": "Int8",
      "cost": "float64", 
      "cost_": "object",
      "price_1": "float64",
      "price_2": "float64",
      "price_3": "float64",
      "price": "float64",
      "sale_price": "object",
      "visible": "bool",
      "title": "object",
      "desc": "object"
    }, 
    "RELEVANT_FIELDS": [
      "id", "quantity", "cost", "field_18653",
      "field_18682", "field_19032", "price", "visible",
      "title",
      "desc"
    ],
    "GSHEET_ID": "1ds3719GaUp7ee-dSKXD3Pf_bJdod0JkVP40fKGW71Jg",
    "COLUMNS": ["B", "G", "H", "J", "P", "Q", "R", "T", "U"],
    "META_KEYS": ["cost",
    "b2bking_regular_product_price_group_2424",
    "b2bking_regular_product_price_group_2425",
    "b2bking_regular_product_price_group_2426",
    "acf-field_65fc592a937b9"]
  }
  